<?xml version="1.0" encoding="UTF-8"?>
<container>
  <rootfiles>
    <rootfile full-path="score_style.mss"/>
    <rootfile full-path="HríslanoglækurinnSATB.mscx"/>
    <rootfile full-path="Excerpts/0_Soprano/0_Soprano.mss"/>
    <rootfile full-path="Excerpts/0_Soprano/0_Soprano.mscx"/>
    <rootfile full-path="Excerpts/1_Part_3/1_Part_3.mss"/>
    <rootfile full-path="Excerpts/1_Part_3/1_Part_3.mscx"/>
    <rootfile full-path="Excerpts/2_Tenor/2_Tenor.mss"/>
    <rootfile full-path="Excerpts/2_Tenor/2_Tenor.mscx"/>
    <rootfile full-path="Excerpts/3_Part_4/3_Part_4.mss"/>
    <rootfile full-path="Excerpts/3_Part_4/3_Part_4.mscx"/>
    <rootfile full-path="Thumbnails/thumbnail.png"/>
    <rootfile full-path="audiosettings.json"/>
    <rootfile full-path="viewsettings.json"/>
    <rootfile full-path="Excerpts/0_Soprano/viewsettings.json"/>
    <rootfile full-path="Excerpts/2_Tenor/viewsettings.json"/>
    <rootfile full-path="Excerpts/1_Part_3/viewsettings.json"/>
    <rootfile full-path="Excerpts/3_Part_4/viewsettings.json"/>
    </rootfiles>
  </container>
